.gitmodules
CMakeLists.txt
noiseflow/__init__.py
noiseflow/cc/__init__.py
noiseflow/cc/include/corr.hpp
noiseflow/cc/include/rfft.hpp
noiseflow/cc/include/stack.hpp
noiseflow/cc/include/utils.hpp
noiseflow/cc/python/__init__.py
noiseflow/cc/python/corr.py
noiseflow/cc/python/rfft.py
noiseflow/cc/python/stack.py
noiseflow/cc/python/utils.py
noiseflow/cc/src/pybind11.cpp
noiseflow/cc/wrapper.py
noiseflow/client/__init__.py
noiseflow/client/client.py
noiseflow/config/__init__.py
noiseflow/config/corrdata.py
noiseflow/config/rawdata.py
noiseflow/config/rfftdata.py
noiseflow/config/stackdata.py
noiseflow/signal/__init__.py
noiseflow/signal/include/decimate.hpp
noiseflow/signal/include/detrend.hpp
noiseflow/signal/include/filter.hpp
noiseflow/signal/include/taper.hpp
noiseflow/signal/include/utils.hpp
noiseflow/signal/python/__init__.py
noiseflow/signal/python/decimate.py
noiseflow/signal/python/detrend.py
noiseflow/signal/python/filter.py
noiseflow/signal/python/taper.py
noiseflow/signal/src/pybind11.cpp
noiseflow/signal/wrapper.py
noiseflow/tests/__init__.py
noiseflow/tests/test_cc/__init__.py
noiseflow/tests/test_cc/test_python/test_corr.py
noiseflow/tests/test_cc/test_python/test_rfft.py
noiseflow/tests/test_cc/test_python/test_stack.py
noiseflow/tests/test_cc/test_python/test_utils.py
noiseflow/tests/test_cc/test_wrapper.py
noiseflow/tests/test_client/__init__.py
noiseflow/tests/test_client/test_client.py
noiseflow/tests/test_config/__init__.py
noiseflow/tests/test_config/test_corrdata.py
noiseflow/tests/test_config/test_rawdata.py
noiseflow/tests/test_config/test_rfftdata.py
noiseflow/tests/test_config/test_stackdata.py
noiseflow/tests/test_signal/__init__.py
noiseflow/tests/test_signal/test_python/__init__.py
noiseflow/tests/test_signal/test_python/test_decimate.py
noiseflow/tests/test_signal/test_python/test_detrend.py
noiseflow/tests/test_signal/test_python/test_filter.py
noiseflow/tests/test_signal/test_python/test_taper.py
noiseflow-0.1.0.dist-info/LICENSE
noiseflow-0.1.0.dist-info/METADATA
noiseflow-0.1.0.dist-info/WHEEL
noiseflow-0.1.0.dist-info/RECORD
