Metadata-Version: 2.1
Name: noiseflow
Version: 0.1.0
Summary: An ambient noise package
License: Apache-2.0
Author: Fu Yin
Author-email: oucyinfu@gmail.com
Requires-Python: >=3.9,<3.12
Classifier: Development Status :: 2 - Pre-Alpha
Classifier: Environment :: Console
Classifier: Intended Audience :: Developers
Classifier: Intended Audience :: Science/Research
Classifier: License :: OSI Approved :: Apache Software License
Classifier: Operating System :: OS Independent
Classifier: Programming Language :: Python
Classifier: Programming Language :: Python :: 3
Classifier: Programming Language :: Python :: 3.9
Classifier: Programming Language :: Python :: 3.10
Classifier: Programming Language :: Python :: 3.11
Classifier: Topic :: Scientific/Engineering
Classifier: Topic :: Scientific/Engineering :: Physics
Provides-Extra: full
Requires-Dist: faker (>=18.13.0,<19.0.0)
Requires-Dist: h5py (>=3.7.0,<4.0.0)
Requires-Dist: joblib (>=1.3.0,<2.0.0)
Requires-Dist: matplotlib (>=3.7.1,<4.0.0)
Requires-Dist: numpy (>=1.25.0,<2.0.0)
Requires-Dist: obspy (>=1.4.0,<2.0.0)
Requires-Dist: scipy (>=1.10.1,<2.0.0)
Requires-Dist: tqdm (>=4.65.0,<5.0.0)
